{
  "id": "mitake-24",
  "name": "24股御岳组",
  "threadCount": 24,
  "source": {
    "kind": "captured-craftdesignonline-stitch-data",
    "endpoint": "mitake.php?cdo_k0=6&cdo_k1=6",
    "formats": "ABC",
    "stitchSize": 2,
    "scale": 9,
    "strokeWidth": 1,
    "bounds": {
      "minX": 1,
      "minY": -2,
      "maxX": 30,
      "maxY": 35
    }
  },
  "canvas": {
    "width": 920,
    "height": 560,
    "surfaceViewBox": "0 0 281 440",
    "diskViewBox": "455 0 465 520",
    "surfaceTransform": "translate(28 16) scale(1.18)"
  },
  "defaultPalette": [
    "#96da52",
    "#272f7c",
    "#88abfb"
  ],
  "diskLayout": {
    "center": {
      "cx": 675,
      "cy": 275
    },
    "radius": 184,
    "threadRadius": 18,
    "groups": [
      {
        "name": "top",
        "label": "Top",
        "angle": 0
      },
      {
        "name": "right",
        "label": "Right",
        "angle": 90
      },
      {
        "name": "bottom",
        "label": "Bottom",
        "angle": 180
      },
      {
        "name": "left",
        "label": "Left",
        "angle": 270
      }
    ],
    "showGroupLabels": false
  },
  "threads": [
    {
      "id": 0,
      "label": "T01",
      "group": "top",
      "defaultColor": "#96da52",
      "disk": {
        "cx": 577.106,
        "cy": 119.203,
        "r": 18
      }
    },
    {
      "id": 1,
      "label": "T02",
      "group": "top",
      "defaultColor": "#96da52",
      "disk": {
        "cx": 614.229,
        "cy": 101.325,
        "r": 18
      }
    },
    {
      "id": 2,
      "label": "T03",
      "group": "top",
      "defaultColor": "#272f7c",
      "disk": {
        "cx": 654.399,
        "cy": 92.157,
        "r": 18
      }
    },
    {
      "id": 3,
      "label": "T04",
      "group": "top",
      "defaultColor": "#272f7c",
      "disk": {
        "cx": 695.601,
        "cy": 92.157,
        "r": 18
      }
    },
    {
      "id": 4,
      "label": "T05",
      "group": "top",
      "defaultColor": "#88abfb",
      "disk": {
        "cx": 735.771,
        "cy": 101.325,
        "r": 18
      }
    },
    {
      "id": 5,
      "label": "T06",
      "group": "top",
      "defaultColor": "#88abfb",
      "disk": {
        "cx": 772.894,
        "cy": 119.203,
        "r": 18
      }
    },
    {
      "id": 6,
      "label": "T07",
      "group": "right",
      "defaultColor": "#88abfb",
      "disk": {
        "cx": 830.797,
        "cy": 177.106,
        "r": 18
      }
    },
    {
      "id": 7,
      "label": "T08",
      "group": "right",
      "defaultColor": "#88abfb",
      "disk": {
        "cx": 848.675,
        "cy": 214.229,
        "r": 18
      }
    },
    {
      "id": 8,
      "label": "T09",
      "group": "right",
      "defaultColor": "#96da52",
      "disk": {
        "cx": 857.843,
        "cy": 254.399,
        "r": 18
      }
    },
    {
      "id": 9,
      "label": "T10",
      "group": "right",
      "defaultColor": "#96da52",
      "disk": {
        "cx": 857.843,
        "cy": 295.601,
        "r": 18
      }
    },
    {
      "id": 10,
      "label": "T11",
      "group": "right",
      "defaultColor": "#272f7c",
      "disk": {
        "cx": 848.675,
        "cy": 335.771,
        "r": 18
      }
    },
    {
      "id": 11,
      "label": "T12",
      "group": "right",
      "defaultColor": "#272f7c",
      "disk": {
        "cx": 830.797,
        "cy": 372.894,
        "r": 18
      }
    },
    {
      "id": 12,
      "label": "T13",
      "group": "bottom",
      "defaultColor": "#272f7c",
      "disk": {
        "cx": 772.894,
        "cy": 430.797,
        "r": 18
      }
    },
    {
      "id": 13,
      "label": "T14",
      "group": "bottom",
      "defaultColor": "#272f7c",
      "disk": {
        "cx": 735.771,
        "cy": 448.675,
        "r": 18
      }
    },
    {
      "id": 14,
      "label": "T15",
      "group": "bottom",
      "defaultColor": "#88abfb",
      "disk": {
        "cx": 695.601,
        "cy": 457.843,
        "r": 18
      }
    },
    {
      "id": 15,
      "label": "T16",
      "group": "bottom",
      "defaultColor": "#88abfb",
      "disk": {
        "cx": 654.399,
        "cy": 457.843,
        "r": 18
      }
    },
    {
      "id": 16,
      "label": "T17",
      "group": "bottom",
      "defaultColor": "#96da52",
      "disk": {
        "cx": 614.229,
        "cy": 448.675,
        "r": 18
      }
    },
    {
      "id": 17,
      "label": "T18",
      "group": "bottom",
      "defaultColor": "#96da52",
      "disk": {
        "cx": 577.106,
        "cy": 430.797,
        "r": 18
      }
    },
    {
      "id": 18,
      "label": "T19",
      "group": "left",
      "defaultColor": "#96da52",
      "disk": {
        "cx": 519.203,
        "cy": 372.894,
        "r": 18
      }
    },
    {
      "id": 19,
      "label": "T20",
      "group": "left",
      "defaultColor": "#96da52",
      "disk": {
        "cx": 501.325,
        "cy": 335.771,
        "r": 18
      }
    },
    {
      "id": 20,
      "label": "T21",
      "group": "left",
      "defaultColor": "#272f7c",
      "disk": {
        "cx": 492.157,
        "cy": 295.601,
        "r": 18
      }
    },
    {
      "id": 21,
      "label": "T22",
      "group": "left",
      "defaultColor": "#272f7c",
      "disk": {
        "cx": 492.157,
        "cy": 254.399,
        "r": 18
      }
    },
    {
      "id": 22,
      "label": "T23",
      "group": "left",
      "defaultColor": "#88abfb",
      "disk": {
        "cx": 501.325,
        "cy": 214.229,
        "r": 18
      }
    },
    {
      "id": 23,
      "label": "T24",
      "group": "left",
      "defaultColor": "#88abfb",
      "disk": {
        "cx": 519.203,
        "cy": 177.106,
        "r": 18
      }
    }
  ],
  "surfaceSegments": [
    {
      "id": "seg-000",
      "threadId": 2,
      "path": "M10,46 A52.479,52.479 0 0,1 28,28 A26.239,26.239 0 0,1 37,37 A78.718,78.718 0 0,1 10,64 A37.108,37.108 0 0,1 10,46 A0,0 0 0,1 10,46"
    },
    {
      "id": "seg-001",
      "threadId": 8,
      "path": "M28,28 A26.239,26.239 0 0,1 37,19 A52.479,52.479 0 0,1 55,37 A26.239,26.239 0 0,1 46,46 A52.479,52.479 0 0,1 28,28 A0,0 0 0,1 28,28"
    },
    {
      "id": "seg-002",
      "threadId": 21,
      "path": "M46,46 A78.718,78.718 0 0,1 73,19 A26.239,26.239 0 0,1 82,28 A78.718,78.718 0 0,1 55,55 A26.239,26.239 0 0,1 46,46 A0,0 0 0,1 46,46"
    },
    {
      "id": "seg-003",
      "threadId": 3,
      "path": "M82,28 A52.479,52.479 0 0,1 100,46 A37.108,37.108 0 0,1 100,64 A78.718,78.718 0 0,1 73,37 A26.239,26.239 0 0,1 82,28 A0,0 0 0,1 82,28"
    },
    {
      "id": "seg-004",
      "threadId": 3,
      "path": "M109,46 A52.479,52.479 0 0,1 127,64 A26.239,26.239 0 0,1 118,73 A26.239,26.239 0 0,1 109,64 A37.108,37.108 0 0,1 109,46 A0,0 0 0,1 109,46"
    },
    {
      "id": "seg-005",
      "threadId": 14,
      "path": "M127,64 A26.239,26.239 0 0,1 118,55 A52.479,52.479 0 0,1 136,37 A37.108,37.108 0 0,1 136,55 A26.239,26.239 0 0,1 127,64 A0,0 0 0,1 127,64"
    },
    {
      "id": "seg-006",
      "threadId": 14,
      "path": "M145,37 A52.479,52.479 0 0,1 163,19 A26.239,26.239 0 0,1 172,28 A78.718,78.718 0 0,1 145,55 A37.108,37.108 0 0,1 145,37 A0,0 0 0,1 145,37"
    },
    {
      "id": "seg-007",
      "threadId": 0,
      "path": "M163,19 A26.239,26.239 0 0,1 172,10 A52.479,52.479 0 0,1 190,28 A26.239,26.239 0 0,1 181,37 A52.479,52.479 0 0,1 163,19 A0,0 0 0,1 163,19"
    },
    {
      "id": "seg-008",
      "threadId": 5,
      "path": "M181,37 A78.718,78.718 0 0,1 208,10 A26.239,26.239 0 0,1 217,19 A78.718,78.718 0 0,1 190,46 A26.239,26.239 0 0,1 181,37 A0,0 0 0,1 181,37"
    },
    {
      "id": "seg-009",
      "threadId": 15,
      "path": "M217,19 A52.479,52.479 0 0,1 235,37 A37.108,37.108 0 0,1 235,55 A78.718,78.718 0 0,1 208,28 A26.239,26.239 0 0,1 217,19 A0,0 0 0,1 217,19"
    },
    {
      "id": "seg-010",
      "threadId": 15,
      "path": "M244,37 A52.479,52.479 0 0,1 262,55 A26.239,26.239 0 0,1 253,64 A26.239,26.239 0 0,1 244,55 A37.108,37.108 0 0,1 244,37 A0,0 0 0,1 244,37"
    },
    {
      "id": "seg-011",
      "threadId": 11,
      "path": "M262,55 A26.239,26.239 0 0,1 253,46 A52.479,52.479 0 0,1 271,28 A37.108,37.108 0 0,1 271,46 A26.239,26.239 0 0,1 262,55 A0,0 0 0,1 262,55"
    },
    {
      "id": "seg-012",
      "threadId": 1,
      "path": "M10,64 A52.479,52.479 0 0,1 28,46 A26.239,26.239 0 0,1 37,55 A78.718,78.718 0 0,1 10,82 A37.108,37.108 0 0,1 10,64 A0,0 0 0,1 10,64"
    },
    {
      "id": "seg-013",
      "threadId": 7,
      "path": "M28,46 A26.239,26.239 0 0,1 37,37 A52.479,52.479 0 0,1 55,55 A26.239,26.239 0 0,1 46,64 A52.479,52.479 0 0,1 28,46 A0,0 0 0,1 28,46"
    },
    {
      "id": "seg-014",
      "threadId": 22,
      "path": "M46,64 A78.718,78.718 0 0,1 73,37 A26.239,26.239 0 0,1 82,46 A78.718,78.718 0 0,1 55,73 A26.239,26.239 0 0,1 46,64 A0,0 0 0,1 46,64"
    },
    {
      "id": "seg-015",
      "threadId": 4,
      "path": "M82,46 A52.479,52.479 0 0,1 100,64 A37.108,37.108 0 0,1 100,82 A78.718,78.718 0 0,1 73,55 A26.239,26.239 0 0,1 82,46 A0,0 0 0,1 82,46"
    },
    {
      "id": "seg-016",
      "threadId": 4,
      "path": "M109,64 A52.479,52.479 0 0,1 127,82 A26.239,26.239 0 0,1 118,91 A26.239,26.239 0 0,1 109,82 A37.108,37.108 0 0,1 109,64 A0,0 0 0,1 109,64"
    },
    {
      "id": "seg-017",
      "threadId": 13,
      "path": "M127,82 A26.239,26.239 0 0,1 118,73 A52.479,52.479 0 0,1 136,55 A37.108,37.108 0 0,1 136,73 A26.239,26.239 0 0,1 127,82 A0,0 0 0,1 127,82"
    },
    {
      "id": "seg-018",
      "threadId": 13,
      "path": "M145,55 A52.479,52.479 0 0,1 163,37 A26.239,26.239 0 0,1 172,46 A78.718,78.718 0 0,1 145,73 A37.108,37.108 0 0,1 145,55 A0,0 0 0,1 145,55"
    },
    {
      "id": "seg-019",
      "threadId": 20,
      "path": "M163,37 A26.239,26.239 0 0,1 172,28 A52.479,52.479 0 0,1 190,46 A26.239,26.239 0 0,1 181,55 A52.479,52.479 0 0,1 163,37 A0,0 0 0,1 163,37"
    },
    {
      "id": "seg-020",
      "threadId": 9,
      "path": "M181,55 A78.718,78.718 0 0,1 208,28 A26.239,26.239 0 0,1 217,37 A78.718,78.718 0 0,1 190,64 A26.239,26.239 0 0,1 181,55 A0,0 0 0,1 181,55"
    },
    {
      "id": "seg-021",
      "threadId": 16,
      "path": "M217,37 A52.479,52.479 0 0,1 235,55 A37.108,37.108 0 0,1 235,73 A78.718,78.718 0 0,1 208,46 A26.239,26.239 0 0,1 217,37 A0,0 0 0,1 217,37"
    },
    {
      "id": "seg-022",
      "threadId": 16,
      "path": "M244,55 A52.479,52.479 0 0,1 262,73 A26.239,26.239 0 0,1 253,82 A26.239,26.239 0 0,1 244,73 A37.108,37.108 0 0,1 244,55 A0,0 0 0,1 244,55"
    },
    {
      "id": "seg-023",
      "threadId": 2,
      "path": "M262,73 A26.239,26.239 0 0,1 253,64 A52.479,52.479 0 0,1 271,46 A37.108,37.108 0 0,1 271,64 A26.239,26.239 0 0,1 262,73 A0,0 0 0,1 262,73"
    },
    {
      "id": "seg-024",
      "threadId": 0,
      "path": "M10,82 A52.479,52.479 0 0,1 28,64 A26.239,26.239 0 0,1 37,73 A78.718,78.718 0 0,1 10,100 A37.108,37.108 0 0,1 10,82 A0,0 0 0,1 10,82"
    },
    {
      "id": "seg-025",
      "threadId": 6,
      "path": "M28,64 A26.239,26.239 0 0,1 37,55 A52.479,52.479 0 0,1 55,73 A26.239,26.239 0 0,1 46,82 A52.479,52.479 0 0,1 28,64 A0,0 0 0,1 28,64"
    },
    {
      "id": "seg-026",
      "threadId": 23,
      "path": "M46,82 A78.718,78.718 0 0,1 73,55 A26.239,26.239 0 0,1 82,64 A78.718,78.718 0 0,1 55,91 A26.239,26.239 0 0,1 46,82 A0,0 0 0,1 46,82"
    },
    {
      "id": "seg-027",
      "threadId": 5,
      "path": "M82,64 A52.479,52.479 0 0,1 100,82 A37.108,37.108 0 0,1 100,100 A78.718,78.718 0 0,1 73,73 A26.239,26.239 0 0,1 82,64 A0,0 0 0,1 82,64"
    },
    {
      "id": "seg-028",
      "threadId": 5,
      "path": "M109,82 A52.479,52.479 0 0,1 127,100 A26.239,26.239 0 0,1 118,109 A26.239,26.239 0 0,1 109,100 A37.108,37.108 0 0,1 109,82 A0,0 0 0,1 109,82"
    },
    {
      "id": "seg-029",
      "threadId": 12,
      "path": "M127,100 A26.239,26.239 0 0,1 118,91 A52.479,52.479 0 0,1 136,73 A37.108,37.108 0 0,1 136,91 A26.239,26.239 0 0,1 127,100 A0,0 0 0,1 127,100"
    },
    {
      "id": "seg-030",
      "threadId": 12,
      "path": "M145,73 A52.479,52.479 0 0,1 163,55 A26.239,26.239 0 0,1 172,64 A78.718,78.718 0 0,1 145,91 A37.108,37.108 0 0,1 145,73 A0,0 0 0,1 145,73"
    },
    {
      "id": "seg-031",
      "threadId": 19,
      "path": "M163,55 A26.239,26.239 0 0,1 172,46 A52.479,52.479 0 0,1 190,64 A26.239,26.239 0 0,1 181,73 A52.479,52.479 0 0,1 163,55 A0,0 0 0,1 163,55"
    },
    {
      "id": "seg-032",
      "threadId": 10,
      "path": "M181,73 A78.718,78.718 0 0,1 208,46 A26.239,26.239 0 0,1 217,55 A78.718,78.718 0 0,1 190,82 A26.239,26.239 0 0,1 181,73 A0,0 0 0,1 181,73"
    },
    {
      "id": "seg-033",
      "threadId": 17,
      "path": "M217,55 A52.479,52.479 0 0,1 235,73 A37.108,37.108 0 0,1 235,91 A78.718,78.718 0 0,1 208,64 A26.239,26.239 0 0,1 217,55 A0,0 0 0,1 217,55"
    },
    {
      "id": "seg-034",
      "threadId": 17,
      "path": "M244,73 A52.479,52.479 0 0,1 262,91 A26.239,26.239 0 0,1 253,100 A26.239,26.239 0 0,1 244,91 A37.108,37.108 0 0,1 244,73 A0,0 0 0,1 244,73"
    },
    {
      "id": "seg-035",
      "threadId": 1,
      "path": "M262,91 A26.239,26.239 0 0,1 253,82 A52.479,52.479 0 0,1 271,64 A37.108,37.108 0 0,1 271,82 A26.239,26.239 0 0,1 262,91 A0,0 0 0,1 262,91"
    },
    {
      "id": "seg-036",
      "threadId": 20,
      "path": "M10,100 A52.479,52.479 0 0,1 28,82 A26.239,26.239 0 0,1 37,91 A78.718,78.718 0 0,1 10,118 A37.108,37.108 0 0,1 10,100 A0,0 0 0,1 10,100"
    },
    {
      "id": "seg-037",
      "threadId": 15,
      "path": "M28,82 A26.239,26.239 0 0,1 37,73 A52.479,52.479 0 0,1 55,91 A26.239,26.239 0 0,1 46,100 A52.479,52.479 0 0,1 28,82 A0,0 0 0,1 28,82"
    },
    {
      "id": "seg-038",
      "threadId": 14,
      "path": "M46,100 A78.718,78.718 0 0,1 73,73 A26.239,26.239 0 0,1 82,82 A78.718,78.718 0 0,1 55,109 A26.239,26.239 0 0,1 46,100 A0,0 0 0,1 46,100"
    },
    {
      "id": "seg-039",
      "threadId": 9,
      "path": "M82,82 A52.479,52.479 0 0,1 100,100 A37.108,37.108 0 0,1 100,118 A78.718,78.718 0 0,1 73,91 A26.239,26.239 0 0,1 82,82 A0,0 0 0,1 82,82"
    },
    {
      "id": "seg-040",
      "threadId": 9,
      "path": "M109,100 A52.479,52.479 0 0,1 127,118 A26.239,26.239 0 0,1 118,127 A26.239,26.239 0 0,1 109,118 A37.108,37.108 0 0,1 109,100 A0,0 0 0,1 109,100"
    },
    {
      "id": "seg-041",
      "threadId": 8,
      "path": "M127,118 A26.239,26.239 0 0,1 118,109 A52.479,52.479 0 0,1 136,91 A37.108,37.108 0 0,1 136,109 A26.239,26.239 0 0,1 127,118 A0,0 0 0,1 127,118"
    },
    {
      "id": "seg-042",
      "threadId": 8,
      "path": "M145,91 A52.479,52.479 0 0,1 163,73 A26.239,26.239 0 0,1 172,82 A78.718,78.718 0 0,1 145,109 A37.108,37.108 0 0,1 145,91 A0,0 0 0,1 145,91"
    },
    {
      "id": "seg-043",
      "threadId": 18,
      "path": "M163,73 A26.239,26.239 0 0,1 172,64 A52.479,52.479 0 0,1 190,82 A26.239,26.239 0 0,1 181,91 A52.479,52.479 0 0,1 163,73 A0,0 0 0,1 163,73"
    },
    {
      "id": "seg-044",
      "threadId": 11,
      "path": "M181,91 A78.718,78.718 0 0,1 208,64 A26.239,26.239 0 0,1 217,73 A78.718,78.718 0 0,1 190,100 A26.239,26.239 0 0,1 181,91 A0,0 0 0,1 181,91"
    },
    {
      "id": "seg-045",
      "threadId": 21,
      "path": "M217,73 A52.479,52.479 0 0,1 235,91 A37.108,37.108 0 0,1 235,109 A78.718,78.718 0 0,1 208,82 A26.239,26.239 0 0,1 217,73 A0,0 0 0,1 217,73"
    },
    {
      "id": "seg-046",
      "threadId": 21,
      "path": "M244,91 A52.479,52.479 0 0,1 262,109 A26.239,26.239 0 0,1 253,118 A26.239,26.239 0 0,1 244,109 A37.108,37.108 0 0,1 244,91 A0,0 0 0,1 244,91"
    },
    {
      "id": "seg-047",
      "threadId": 0,
      "path": "M262,109 A26.239,26.239 0 0,1 253,100 A52.479,52.479 0 0,1 271,82 A37.108,37.108 0 0,1 271,100 A26.239,26.239 0 0,1 262,109 A0,0 0 0,1 262,109"
    },
    {
      "id": "seg-048",
      "threadId": 19,
      "path": "M10,118 A52.479,52.479 0 0,1 28,100 A26.239,26.239 0 0,1 37,109 A78.718,78.718 0 0,1 10,136 A37.108,37.108 0 0,1 10,118 A0,0 0 0,1 10,118"
    },
    {
      "id": "seg-049",
      "threadId": 16,
      "path": "M28,100 A26.239,26.239 0 0,1 37,91 A52.479,52.479 0 0,1 55,109 A26.239,26.239 0 0,1 46,118 A52.479,52.479 0 0,1 28,100 A0,0 0 0,1 28,100"
    },
    {
      "id": "seg-050",
      "threadId": 13,
      "path": "M46,118 A78.718,78.718 0 0,1 73,91 A26.239,26.239 0 0,1 82,100 A78.718,78.718 0 0,1 55,127 A26.239,26.239 0 0,1 46,118 A0,0 0 0,1 46,118"
    },
    {
      "id": "seg-051",
      "threadId": 10,
      "path": "M82,100 A52.479,52.479 0 0,1 100,118 A37.108,37.108 0 0,1 100,136 A78.718,78.718 0 0,1 73,109 A26.239,26.239 0 0,1 82,100 A0,0 0 0,1 82,100"
    },
    {
      "id": "seg-052",
      "threadId": 10,
      "path": "M109,118 A52.479,52.479 0 0,1 127,136 A26.239,26.239 0 0,1 118,145 A26.239,26.239 0 0,1 109,136 A37.108,37.108 0 0,1 109,118 A0,0 0 0,1 109,118"
    },
    {
      "id": "seg-053",
      "threadId": 7,
      "path": "M127,136 A26.239,26.239 0 0,1 118,127 A52.479,52.479 0 0,1 136,109 A37.108,37.108 0 0,1 136,127 A26.239,26.239 0 0,1 127,136 A0,0 0 0,1 127,136"
    },
    {
      "id": "seg-054",
      "threadId": 7,
      "path": "M145,109 A52.479,52.479 0 0,1 163,91 A26.239,26.239 0 0,1 172,100 A78.718,78.718 0 0,1 145,127 A37.108,37.108 0 0,1 145,109 A0,0 0 0,1 145,109"
    },
    {
      "id": "seg-055",
      "threadId": 3,
      "path": "M163,91 A26.239,26.239 0 0,1 172,82 A52.479,52.479 0 0,1 190,100 A26.239,26.239 0 0,1 181,109 A52.479,52.479 0 0,1 163,91 A0,0 0 0,1 163,91"
    },
    {
      "id": "seg-056",
      "threadId": 2,
      "path": "M181,109 A78.718,78.718 0 0,1 208,82 A26.239,26.239 0 0,1 217,91 A78.718,78.718 0 0,1 190,118 A26.239,26.239 0 0,1 181,109 A0,0 0 0,1 181,109"
    },
    {
      "id": "seg-057",
      "threadId": 22,
      "path": "M217,91 A52.479,52.479 0 0,1 235,109 A37.108,37.108 0 0,1 235,127 A78.718,78.718 0 0,1 208,100 A26.239,26.239 0 0,1 217,91 A0,0 0 0,1 217,91"
    },
    {
      "id": "seg-058",
      "threadId": 22,
      "path": "M244,109 A52.479,52.479 0 0,1 262,127 A26.239,26.239 0 0,1 253,136 A26.239,26.239 0 0,1 244,127 A37.108,37.108 0 0,1 244,109 A0,0 0 0,1 244,109"
    },
    {
      "id": "seg-059",
      "threadId": 20,
      "path": "M262,127 A26.239,26.239 0 0,1 253,118 A52.479,52.479 0 0,1 271,100 A37.108,37.108 0 0,1 271,118 A26.239,26.239 0 0,1 262,127 A0,0 0 0,1 262,127"
    },
    {
      "id": "seg-060",
      "threadId": 18,
      "path": "M10,136 A52.479,52.479 0 0,1 28,118 A26.239,26.239 0 0,1 37,127 A78.718,78.718 0 0,1 10,154 A37.108,37.108 0 0,1 10,136 A0,0 0 0,1 10,136"
    },
    {
      "id": "seg-061",
      "threadId": 17,
      "path": "M28,118 A26.239,26.239 0 0,1 37,109 A52.479,52.479 0 0,1 55,127 A26.239,26.239 0 0,1 46,136 A52.479,52.479 0 0,1 28,118 A0,0 0 0,1 28,118"
    },
    {
      "id": "seg-062",
      "threadId": 12,
      "path": "M46,136 A78.718,78.718 0 0,1 73,109 A26.239,26.239 0 0,1 82,118 A78.718,78.718 0 0,1 55,145 A26.239,26.239 0 0,1 46,136 A0,0 0 0,1 46,136"
    },
    {
      "id": "seg-063",
      "threadId": 11,
      "path": "M82,118 A52.479,52.479 0 0,1 100,136 A37.108,37.108 0 0,1 100,154 A78.718,78.718 0 0,1 73,127 A26.239,26.239 0 0,1 82,118 A0,0 0 0,1 82,118"
    },
    {
      "id": "seg-064",
      "threadId": 11,
      "path": "M109,136 A52.479,52.479 0 0,1 127,154 A26.239,26.239 0 0,1 118,163 A26.239,26.239 0 0,1 109,154 A37.108,37.108 0 0,1 109,136 A0,0 0 0,1 109,136"
    },
    {
      "id": "seg-065",
      "threadId": 6,
      "path": "M127,154 A26.239,26.239 0 0,1 118,145 A52.479,52.479 0 0,1 136,127 A37.108,37.108 0 0,1 136,145 A26.239,26.239 0 0,1 127,154 A0,0 0 0,1 127,154"
    },
    {
      "id": "seg-066",
      "threadId": 6,
      "path": "M145,127 A52.479,52.479 0 0,1 163,109 A26.239,26.239 0 0,1 172,118 A78.718,78.718 0 0,1 145,145 A37.108,37.108 0 0,1 145,127 A0,0 0 0,1 145,127"
    },
    {
      "id": "seg-067",
      "threadId": 4,
      "path": "M163,109 A26.239,26.239 0 0,1 172,100 A52.479,52.479 0 0,1 190,118 A26.239,26.239 0 0,1 181,127 A52.479,52.479 0 0,1 163,109 A0,0 0 0,1 163,109"
    },
    {
      "id": "seg-068",
      "threadId": 1,
      "path": "M181,127 A78.718,78.718 0 0,1 208,100 A26.239,26.239 0 0,1 217,109 A78.718,78.718 0 0,1 190,136 A26.239,26.239 0 0,1 181,127 A0,0 0 0,1 181,127"
    },
    {
      "id": "seg-069",
      "threadId": 23,
      "path": "M217,109 A52.479,52.479 0 0,1 235,127 A37.108,37.108 0 0,1 235,145 A78.718,78.718 0 0,1 208,118 A26.239,26.239 0 0,1 217,109 A0,0 0 0,1 217,109"
    },
    {
      "id": "seg-070",
      "threadId": 23,
      "path": "M244,127 A52.479,52.479 0 0,1 262,145 A26.239,26.239 0 0,1 253,154 A26.239,26.239 0 0,1 244,145 A37.108,37.108 0 0,1 244,127 A0,0 0 0,1 244,127"
    },
    {
      "id": "seg-071",
      "threadId": 19,
      "path": "M262,145 A26.239,26.239 0 0,1 253,136 A52.479,52.479 0 0,1 271,118 A37.108,37.108 0 0,1 271,136 A26.239,26.239 0 0,1 262,145 A0,0 0 0,1 262,145"
    },
    {
      "id": "seg-072",
      "threadId": 3,
      "path": "M10,154 A52.479,52.479 0 0,1 28,136 A26.239,26.239 0 0,1 37,145 A78.718,78.718 0 0,1 10,172 A37.108,37.108 0 0,1 10,154 A0,0 0 0,1 10,154"
    },
    {
      "id": "seg-073",
      "threadId": 21,
      "path": "M28,136 A26.239,26.239 0 0,1 37,127 A52.479,52.479 0 0,1 55,145 A26.239,26.239 0 0,1 46,154 A52.479,52.479 0 0,1 28,136 A0,0 0 0,1 28,136"
    },
    {
      "id": "seg-074",
      "threadId": 8,
      "path": "M46,154 A78.718,78.718 0 0,1 73,127 A26.239,26.239 0 0,1 82,136 A78.718,78.718 0 0,1 55,163 A26.239,26.239 0 0,1 46,154 A0,0 0 0,1 46,154"
    },
    {
      "id": "seg-075",
      "threadId": 2,
      "path": "M82,136 A52.479,52.479 0 0,1 100,154 A37.108,37.108 0 0,1 100,172 A78.718,78.718 0 0,1 73,145 A26.239,26.239 0 0,1 82,136 A0,0 0 0,1 82,136"
    },
    {
      "id": "seg-076",
      "threadId": 2,
      "path": "M109,154 A52.479,52.479 0 0,1 127,172 A26.239,26.239 0 0,1 118,181 A26.239,26.239 0 0,1 109,172 A37.108,37.108 0 0,1 109,154 A0,0 0 0,1 109,154"
    },
    {
      "id": "seg-077",
      "threadId": 15,
      "path": "M127,172 A26.239,26.239 0 0,1 118,163 A52.479,52.479 0 0,1 136,145 A37.108,37.108 0 0,1 136,163 A26.239,26.239 0 0,1 127,172 A0,0 0 0,1 127,172"
    },
    {
      "id": "seg-078",
      "threadId": 15,
      "path": "M145,145 A52.479,52.479 0 0,1 163,127 A26.239,26.239 0 0,1 172,136 A78.718,78.718 0 0,1 145,163 A37.108,37.108 0 0,1 145,145 A0,0 0 0,1 145,145"
    },
    {
      "id": "seg-079",
      "threadId": 5,
      "path": "M163,127 A26.239,26.239 0 0,1 172,118 A52.479,52.479 0 0,1 190,136 A26.239,26.239 0 0,1 181,145 A52.479,52.479 0 0,1 163,127 A0,0 0 0,1 163,127"
    },
    {
      "id": "seg-080",
      "threadId": 0,
      "path": "M181,145 A78.718,78.718 0 0,1 208,118 A26.239,26.239 0 0,1 217,127 A78.718,78.718 0 0,1 190,154 A26.239,26.239 0 0,1 181,145 A0,0 0 0,1 181,145"
    },
    {
      "id": "seg-081",
      "threadId": 14,
      "path": "M217,127 A52.479,52.479 0 0,1 235,145 A37.108,37.108 0 0,1 235,163 A78.718,78.718 0 0,1 208,136 A26.239,26.239 0 0,1 217,127 A0,0 0 0,1 217,127"
    },
    {
      "id": "seg-082",
      "threadId": 14,
      "path": "M244,145 A52.479,52.479 0 0,1 262,163 A26.239,26.239 0 0,1 253,172 A26.239,26.239 0 0,1 244,163 A37.108,37.108 0 0,1 244,145 A0,0 0 0,1 244,145"
    },
    {
      "id": "seg-083",
      "threadId": 18,
      "path": "M262,163 A26.239,26.239 0 0,1 253,154 A52.479,52.479 0 0,1 271,136 A37.108,37.108 0 0,1 271,154 A26.239,26.239 0 0,1 262,163 A0,0 0 0,1 262,163"
    },
    {
      "id": "seg-084",
      "threadId": 4,
      "path": "M10,172 A52.479,52.479 0 0,1 28,154 A26.239,26.239 0 0,1 37,163 A78.718,78.718 0 0,1 10,190 A37.108,37.108 0 0,1 10,172 A0,0 0 0,1 10,172"
    },
    {
      "id": "seg-085",
      "threadId": 22,
      "path": "M28,154 A26.239,26.239 0 0,1 37,145 A52.479,52.479 0 0,1 55,163 A26.239,26.239 0 0,1 46,172 A52.479,52.479 0 0,1 28,154 A0,0 0 0,1 28,154"
    },
    {
      "id": "seg-086",
      "threadId": 7,
      "path": "M46,172 A78.718,78.718 0 0,1 73,145 A26.239,26.239 0 0,1 82,154 A78.718,78.718 0 0,1 55,181 A26.239,26.239 0 0,1 46,172 A0,0 0 0,1 46,172"
    },
    {
      "id": "seg-087",
      "threadId": 1,
      "path": "M82,154 A52.479,52.479 0 0,1 100,172 A37.108,37.108 0 0,1 100,190 A78.718,78.718 0 0,1 73,163 A26.239,26.239 0 0,1 82,154 A0,0 0 0,1 82,154"
    },
    {
      "id": "seg-088",
      "threadId": 1,
      "path": "M109,172 A52.479,52.479 0 0,1 127,190 A26.239,26.239 0 0,1 118,199 A26.239,26.239 0 0,1 109,190 A37.108,37.108 0 0,1 109,172 A0,0 0 0,1 109,172"
    },
    {
      "id": "seg-089",
      "threadId": 16,
      "path": "M127,190 A26.239,26.239 0 0,1 118,181 A52.479,52.479 0 0,1 136,163 A37.108,37.108 0 0,1 136,181 A26.239,26.239 0 0,1 127,190 A0,0 0 0,1 127,190"
    },
    {
      "id": "seg-090",
      "threadId": 16,
      "path": "M145,163 A52.479,52.479 0 0,1 163,145 A26.239,26.239 0 0,1 172,154 A78.718,78.718 0 0,1 145,181 A37.108,37.108 0 0,1 145,163 A0,0 0 0,1 145,163"
    },
    {
      "id": "seg-091",
      "threadId": 9,
      "path": "M163,145 A26.239,26.239 0 0,1 172,136 A52.479,52.479 0 0,1 190,154 A26.239,26.239 0 0,1 181,163 A52.479,52.479 0 0,1 163,145 A0,0 0 0,1 163,145"
    },
    {
      "id": "seg-092",
      "threadId": 20,
      "path": "M181,163 A78.718,78.718 0 0,1 208,136 A26.239,26.239 0 0,1 217,145 A78.718,78.718 0 0,1 190,172 A26.239,26.239 0 0,1 181,163 A0,0 0 0,1 181,163"
    },
    {
      "id": "seg-093",
      "threadId": 13,
      "path": "M217,145 A52.479,52.479 0 0,1 235,163 A37.108,37.108 0 0,1 235,181 A78.718,78.718 0 0,1 208,154 A26.239,26.239 0 0,1 217,145 A0,0 0 0,1 217,145"
    },
    {
      "id": "seg-094",
      "threadId": 13,
      "path": "M244,163 A52.479,52.479 0 0,1 262,181 A26.239,26.239 0 0,1 253,190 A26.239,26.239 0 0,1 244,181 A37.108,37.108 0 0,1 244,163 A0,0 0 0,1 244,163"
    },
    {
      "id": "seg-095",
      "threadId": 3,
      "path": "M262,181 A26.239,26.239 0 0,1 253,172 A52.479,52.479 0 0,1 271,154 A37.108,37.108 0 0,1 271,172 A26.239,26.239 0 0,1 262,181 A0,0 0 0,1 262,181"
    },
    {
      "id": "seg-096",
      "threadId": 5,
      "path": "M10,190 A52.479,52.479 0 0,1 28,172 A26.239,26.239 0 0,1 37,181 A78.718,78.718 0 0,1 10,208 A37.108,37.108 0 0,1 10,190 A0,0 0 0,1 10,190"
    },
    {
      "id": "seg-097",
      "threadId": 23,
      "path": "M28,172 A26.239,26.239 0 0,1 37,163 A52.479,52.479 0 0,1 55,181 A26.239,26.239 0 0,1 46,190 A52.479,52.479 0 0,1 28,172 A0,0 0 0,1 28,172"
    },
    {
      "id": "seg-098",
      "threadId": 6,
      "path": "M46,190 A78.718,78.718 0 0,1 73,163 A26.239,26.239 0 0,1 82,172 A78.718,78.718 0 0,1 55,199 A26.239,26.239 0 0,1 46,190 A0,0 0 0,1 46,190"
    },
    {
      "id": "seg-099",
      "threadId": 0,
      "path": "M82,172 A52.479,52.479 0 0,1 100,190 A37.108,37.108 0 0,1 100,208 A78.718,78.718 0 0,1 73,181 A26.239,26.239 0 0,1 82,172 A0,0 0 0,1 82,172"
    },
    {
      "id": "seg-100",
      "threadId": 0,
      "path": "M109,190 A52.479,52.479 0 0,1 127,208 A26.239,26.239 0 0,1 118,217 A26.239,26.239 0 0,1 109,208 A37.108,37.108 0 0,1 109,190 A0,0 0 0,1 109,190"
    },
    {
      "id": "seg-101",
      "threadId": 17,
      "path": "M127,208 A26.239,26.239 0 0,1 118,199 A52.479,52.479 0 0,1 136,181 A37.108,37.108 0 0,1 136,199 A26.239,26.239 0 0,1 127,208 A0,0 0 0,1 127,208"
    },
    {
      "id": "seg-102",
      "threadId": 17,
      "path": "M145,181 A52.479,52.479 0 0,1 163,163 A26.239,26.239 0 0,1 172,172 A78.718,78.718 0 0,1 145,199 A37.108,37.108 0 0,1 145,181 A0,0 0 0,1 145,181"
    },
    {
      "id": "seg-103",
      "threadId": 10,
      "path": "M163,163 A26.239,26.239 0 0,1 172,154 A52.479,52.479 0 0,1 190,172 A26.239,26.239 0 0,1 181,181 A52.479,52.479 0 0,1 163,163 A0,0 0 0,1 163,163"
    },
    {
      "id": "seg-104",
      "threadId": 19,
      "path": "M181,181 A78.718,78.718 0 0,1 208,154 A26.239,26.239 0 0,1 217,163 A78.718,78.718 0 0,1 190,190 A26.239,26.239 0 0,1 181,181 A0,0 0 0,1 181,181"
    },
    {
      "id": "seg-105",
      "threadId": 12,
      "path": "M217,163 A52.479,52.479 0 0,1 235,181 A37.108,37.108 0 0,1 235,199 A78.718,78.718 0 0,1 208,172 A26.239,26.239 0 0,1 217,163 A0,0 0 0,1 217,163"
    },
    {
      "id": "seg-106",
      "threadId": 12,
      "path": "M244,181 A52.479,52.479 0 0,1 262,199 A26.239,26.239 0 0,1 253,208 A26.239,26.239 0 0,1 244,199 A37.108,37.108 0 0,1 244,181 A0,0 0 0,1 244,181"
    },
    {
      "id": "seg-107",
      "threadId": 4,
      "path": "M262,199 A26.239,26.239 0 0,1 253,190 A52.479,52.479 0 0,1 271,172 A37.108,37.108 0 0,1 271,190 A26.239,26.239 0 0,1 262,199 A0,0 0 0,1 262,199"
    },
    {
      "id": "seg-108",
      "threadId": 9,
      "path": "M10,208 A52.479,52.479 0 0,1 28,190 A26.239,26.239 0 0,1 37,199 A78.718,78.718 0 0,1 10,226 A37.108,37.108 0 0,1 10,208 A0,0 0 0,1 10,208"
    },
    {
      "id": "seg-109",
      "threadId": 14,
      "path": "M28,190 A26.239,26.239 0 0,1 37,181 A52.479,52.479 0 0,1 55,199 A26.239,26.239 0 0,1 46,208 A52.479,52.479 0 0,1 28,190 A0,0 0 0,1 28,190"
    },
    {
      "id": "seg-110",
      "threadId": 15,
      "path": "M46,208 A78.718,78.718 0 0,1 73,181 A26.239,26.239 0 0,1 82,190 A78.718,78.718 0 0,1 55,217 A26.239,26.239 0 0,1 46,208 A0,0 0 0,1 46,208"
    },
    {
      "id": "seg-111",
      "threadId": 20,
      "path": "M82,190 A52.479,52.479 0 0,1 100,208 A37.108,37.108 0 0,1 100,226 A78.718,78.718 0 0,1 73,199 A26.239,26.239 0 0,1 82,190 A0,0 0 0,1 82,190"
    },
    {
      "id": "seg-112",
      "threadId": 20,
      "path": "M109,208 A52.479,52.479 0 0,1 127,226 A26.239,26.239 0 0,1 118,235 A26.239,26.239 0 0,1 109,226 A37.108,37.108 0 0,1 109,208 A0,0 0 0,1 109,208"
    },
    {
      "id": "seg-113",
      "threadId": 21,
      "path": "M127,226 A26.239,26.239 0 0,1 118,217 A52.479,52.479 0 0,1 136,199 A37.108,37.108 0 0,1 136,217 A26.239,26.239 0 0,1 127,226 A0,0 0 0,1 127,226"
    },
    {
      "id": "seg-114",
      "threadId": 21,
      "path": "M145,199 A52.479,52.479 0 0,1 163,181 A26.239,26.239 0 0,1 172,190 A78.718,78.718 0 0,1 145,217 A37.108,37.108 0 0,1 145,199 A0,0 0 0,1 145,199"
    },
    {
      "id": "seg-115",
      "threadId": 11,
      "path": "M163,181 A26.239,26.239 0 0,1 172,172 A52.479,52.479 0 0,1 190,190 A26.239,26.239 0 0,1 181,199 A52.479,52.479 0 0,1 163,181 A0,0 0 0,1 163,181"
    },
    {
      "id": "seg-116",
      "threadId": 18,
      "path": "M181,199 A78.718,78.718 0 0,1 208,172 A26.239,26.239 0 0,1 217,181 A78.718,78.718 0 0,1 190,208 A26.239,26.239 0 0,1 181,199 A0,0 0 0,1 181,199"
    },
    {
      "id": "seg-117",
      "threadId": 8,
      "path": "M217,181 A52.479,52.479 0 0,1 235,199 A37.108,37.108 0 0,1 235,217 A78.718,78.718 0 0,1 208,190 A26.239,26.239 0 0,1 217,181 A0,0 0 0,1 217,181"
    },
    {
      "id": "seg-118",
      "threadId": 8,
      "path": "M244,199 A52.479,52.479 0 0,1 262,217 A26.239,26.239 0 0,1 253,226 A26.239,26.239 0 0,1 244,217 A37.108,37.108 0 0,1 244,199 A0,0 0 0,1 244,199"
    },
    {
      "id": "seg-119",
      "threadId": 5,
      "path": "M262,217 A26.239,26.239 0 0,1 253,208 A52.479,52.479 0 0,1 271,190 A37.108,37.108 0 0,1 271,208 A26.239,26.239 0 0,1 262,217 A0,0 0 0,1 262,217"
    },
    {
      "id": "seg-120",
      "threadId": 10,
      "path": "M10,226 A52.479,52.479 0 0,1 28,208 A26.239,26.239 0 0,1 37,217 A78.718,78.718 0 0,1 10,244 A37.108,37.108 0 0,1 10,226 A0,0 0 0,1 10,226"
    },
    {
      "id": "seg-121",
      "threadId": 13,
      "path": "M28,208 A26.239,26.239 0 0,1 37,199 A52.479,52.479 0 0,1 55,217 A26.239,26.239 0 0,1 46,226 A52.479,52.479 0 0,1 28,208 A0,0 0 0,1 28,208"
    },
    {
      "id": "seg-122",
      "threadId": 16,
      "path": "M46,226 A78.718,78.718 0 0,1 73,199 A26.239,26.239 0 0,1 82,208 A78.718,78.718 0 0,1 55,235 A26.239,26.239 0 0,1 46,226 A0,0 0 0,1 46,226"
    },
    {
      "id": "seg-123",
      "threadId": 19,
      "path": "M82,208 A52.479,52.479 0 0,1 100,226 A37.108,37.108 0 0,1 100,244 A78.718,78.718 0 0,1 73,217 A26.239,26.239 0 0,1 82,208 A0,0 0 0,1 82,208"
    },
    {
      "id": "seg-124",
      "threadId": 19,
      "path": "M109,226 A52.479,52.479 0 0,1 127,244 A26.239,26.239 0 0,1 118,253 A26.239,26.239 0 0,1 109,244 A37.108,37.108 0 0,1 109,226 A0,0 0 0,1 109,226"
    },
    {
      "id": "seg-125",
      "threadId": 22,
      "path": "M127,244 A26.239,26.239 0 0,1 118,235 A52.479,52.479 0 0,1 136,217 A37.108,37.108 0 0,1 136,235 A26.239,26.239 0 0,1 127,244 A0,0 0 0,1 127,244"
    },
    {
      "id": "seg-126",
      "threadId": 22,
      "path": "M145,217 A52.479,52.479 0 0,1 163,199 A26.239,26.239 0 0,1 172,208 A78.718,78.718 0 0,1 145,235 A37.108,37.108 0 0,1 145,217 A0,0 0 0,1 145,217"
    },
    {
      "id": "seg-127",
      "threadId": 2,
      "path": "M163,199 A26.239,26.239 0 0,1 172,190 A52.479,52.479 0 0,1 190,208 A26.239,26.239 0 0,1 181,217 A52.479,52.479 0 0,1 163,199 A0,0 0 0,1 163,199"
    },
    {
      "id": "seg-128",
      "threadId": 3,
      "path": "M181,217 A78.718,78.718 0 0,1 208,190 A26.239,26.239 0 0,1 217,199 A78.718,78.718 0 0,1 190,226 A26.239,26.239 0 0,1 181,217 A0,0 0 0,1 181,217"
    },
    {
      "id": "seg-129",
      "threadId": 7,
      "path": "M217,199 A52.479,52.479 0 0,1 235,217 A37.108,37.108 0 0,1 235,235 A78.718,78.718 0 0,1 208,208 A26.239,26.239 0 0,1 217,199 A0,0 0 0,1 217,199"
    },
    {
      "id": "seg-130",
      "threadId": 7,
      "path": "M244,217 A52.479,52.479 0 0,1 262,235 A26.239,26.239 0 0,1 253,244 A26.239,26.239 0 0,1 244,235 A37.108,37.108 0 0,1 244,217 A0,0 0 0,1 244,217"
    },
    {
      "id": "seg-131",
      "threadId": 9,
      "path": "M262,235 A26.239,26.239 0 0,1 253,226 A52.479,52.479 0 0,1 271,208 A37.108,37.108 0 0,1 271,226 A26.239,26.239 0 0,1 262,235 A0,0 0 0,1 262,235"
    },
    {
      "id": "seg-132",
      "threadId": 11,
      "path": "M10,244 A52.479,52.479 0 0,1 28,226 A26.239,26.239 0 0,1 37,235 A78.718,78.718 0 0,1 10,262 A37.108,37.108 0 0,1 10,244 A0,0 0 0,1 10,244"
    },
    {
      "id": "seg-133",
      "threadId": 12,
      "path": "M28,226 A26.239,26.239 0 0,1 37,217 A52.479,52.479 0 0,1 55,235 A26.239,26.239 0 0,1 46,244 A52.479,52.479 0 0,1 28,226 A0,0 0 0,1 28,226"
    },
    {
      "id": "seg-134",
      "threadId": 17,
      "path": "M46,244 A78.718,78.718 0 0,1 73,217 A26.239,26.239 0 0,1 82,226 A78.718,78.718 0 0,1 55,253 A26.239,26.239 0 0,1 46,244 A0,0 0 0,1 46,244"
    },
    {
      "id": "seg-135",
      "threadId": 18,
      "path": "M82,226 A52.479,52.479 0 0,1 100,244 A37.108,37.108 0 0,1 100,262 A78.718,78.718 0 0,1 73,235 A26.239,26.239 0 0,1 82,226 A0,0 0 0,1 82,226"
    },
    {
      "id": "seg-136",
      "threadId": 18,
      "path": "M109,244 A52.479,52.479 0 0,1 127,262 A26.239,26.239 0 0,1 118,271 A26.239,26.239 0 0,1 109,262 A37.108,37.108 0 0,1 109,244 A0,0 0 0,1 109,244"
    },
    {
      "id": "seg-137",
      "threadId": 23,
      "path": "M127,262 A26.239,26.239 0 0,1 118,253 A52.479,52.479 0 0,1 136,235 A37.108,37.108 0 0,1 136,253 A26.239,26.239 0 0,1 127,262 A0,0 0 0,1 127,262"
    },
    {
      "id": "seg-138",
      "threadId": 23,
      "path": "M145,235 A52.479,52.479 0 0,1 163,217 A26.239,26.239 0 0,1 172,226 A78.718,78.718 0 0,1 145,253 A37.108,37.108 0 0,1 145,235 A0,0 0 0,1 145,235"
    },
    {
      "id": "seg-139",
      "threadId": 1,
      "path": "M163,217 A26.239,26.239 0 0,1 172,208 A52.479,52.479 0 0,1 190,226 A26.239,26.239 0 0,1 181,235 A52.479,52.479 0 0,1 163,217 A0,0 0 0,1 163,217"
    },
    {
      "id": "seg-140",
      "threadId": 4,
      "path": "M181,235 A78.718,78.718 0 0,1 208,208 A26.239,26.239 0 0,1 217,217 A78.718,78.718 0 0,1 190,244 A26.239,26.239 0 0,1 181,235 A0,0 0 0,1 181,235"
    },
    {
      "id": "seg-141",
      "threadId": 6,
      "path": "M217,217 A52.479,52.479 0 0,1 235,235 A37.108,37.108 0 0,1 235,253 A78.718,78.718 0 0,1 208,226 A26.239,26.239 0 0,1 217,217 A0,0 0 0,1 217,217"
    },
    {
      "id": "seg-142",
      "threadId": 6,
      "path": "M244,235 A52.479,52.479 0 0,1 262,253 A26.239,26.239 0 0,1 253,262 A26.239,26.239 0 0,1 244,253 A37.108,37.108 0 0,1 244,235 A0,0 0 0,1 244,235"
    },
    {
      "id": "seg-143",
      "threadId": 10,
      "path": "M262,253 A26.239,26.239 0 0,1 253,244 A52.479,52.479 0 0,1 271,226 A37.108,37.108 0 0,1 271,244 A26.239,26.239 0 0,1 262,253 A0,0 0 0,1 262,253"
    },
    {
      "id": "seg-144",
      "threadId": 2,
      "path": "M10,262 A52.479,52.479 0 0,1 28,244 A26.239,26.239 0 0,1 37,253 A78.718,78.718 0 0,1 10,280 A37.108,37.108 0 0,1 10,262 A0,0 0 0,1 10,262"
    },
    {
      "id": "seg-145",
      "threadId": 8,
      "path": "M28,244 A26.239,26.239 0 0,1 37,235 A52.479,52.479 0 0,1 55,253 A26.239,26.239 0 0,1 46,262 A52.479,52.479 0 0,1 28,244 A0,0 0 0,1 28,244"
    },
    {
      "id": "seg-146",
      "threadId": 21,
      "path": "M46,262 A78.718,78.718 0 0,1 73,235 A26.239,26.239 0 0,1 82,244 A78.718,78.718 0 0,1 55,271 A26.239,26.239 0 0,1 46,262 A0,0 0 0,1 46,262"
    },
    {
      "id": "seg-147",
      "threadId": 3,
      "path": "M82,244 A52.479,52.479 0 0,1 100,262 A37.108,37.108 0 0,1 100,280 A78.718,78.718 0 0,1 73,253 A26.239,26.239 0 0,1 82,244 A0,0 0 0,1 82,244"
    },
    {
      "id": "seg-148",
      "threadId": 3,
      "path": "M109,262 A52.479,52.479 0 0,1 127,280 A26.239,26.239 0 0,1 118,289 A26.239,26.239 0 0,1 109,280 A37.108,37.108 0 0,1 109,262 A0,0 0 0,1 109,262"
    },
    {
      "id": "seg-149",
      "threadId": 14,
      "path": "M127,280 A26.239,26.239 0 0,1 118,271 A52.479,52.479 0 0,1 136,253 A37.108,37.108 0 0,1 136,271 A26.239,26.239 0 0,1 127,280 A0,0 0 0,1 127,280"
    },
    {
      "id": "seg-150",
      "threadId": 14,
      "path": "M145,253 A52.479,52.479 0 0,1 163,235 A26.239,26.239 0 0,1 172,244 A78.718,78.718 0 0,1 145,271 A37.108,37.108 0 0,1 145,253 A0,0 0 0,1 145,253"
    },
    {
      "id": "seg-151",
      "threadId": 0,
      "path": "M163,235 A26.239,26.239 0 0,1 172,226 A52.479,52.479 0 0,1 190,244 A26.239,26.239 0 0,1 181,253 A52.479,52.479 0 0,1 163,235 A0,0 0 0,1 163,235"
    },
    {
      "id": "seg-152",
      "threadId": 5,
      "path": "M181,253 A78.718,78.718 0 0,1 208,226 A26.239,26.239 0 0,1 217,235 A78.718,78.718 0 0,1 190,262 A26.239,26.239 0 0,1 181,253 A0,0 0 0,1 181,253"
    },
    {
      "id": "seg-153",
      "threadId": 15,
      "path": "M217,235 A52.479,52.479 0 0,1 235,253 A37.108,37.108 0 0,1 235,271 A78.718,78.718 0 0,1 208,244 A26.239,26.239 0 0,1 217,235 A0,0 0 0,1 217,235"
    },
    {
      "id": "seg-154",
      "threadId": 15,
      "path": "M244,253 A52.479,52.479 0 0,1 262,271 A26.239,26.239 0 0,1 253,280 A26.239,26.239 0 0,1 244,271 A37.108,37.108 0 0,1 244,253 A0,0 0 0,1 244,253"
    },
    {
      "id": "seg-155",
      "threadId": 11,
      "path": "M262,271 A26.239,26.239 0 0,1 253,262 A52.479,52.479 0 0,1 271,244 A37.108,37.108 0 0,1 271,262 A26.239,26.239 0 0,1 262,271 A0,0 0 0,1 262,271"
    },
    {
      "id": "seg-156",
      "threadId": 1,
      "path": "M10,280 A52.479,52.479 0 0,1 28,262 A26.239,26.239 0 0,1 37,271 A78.718,78.718 0 0,1 10,298 A37.108,37.108 0 0,1 10,280 A0,0 0 0,1 10,280"
    },
    {
      "id": "seg-157",
      "threadId": 7,
      "path": "M28,262 A26.239,26.239 0 0,1 37,253 A52.479,52.479 0 0,1 55,271 A26.239,26.239 0 0,1 46,280 A52.479,52.479 0 0,1 28,262 A0,0 0 0,1 28,262"
    },
    {
      "id": "seg-158",
      "threadId": 22,
      "path": "M46,280 A78.718,78.718 0 0,1 73,253 A26.239,26.239 0 0,1 82,262 A78.718,78.718 0 0,1 55,289 A26.239,26.239 0 0,1 46,280 A0,0 0 0,1 46,280"
    },
    {
      "id": "seg-159",
      "threadId": 4,
      "path": "M82,262 A52.479,52.479 0 0,1 100,280 A37.108,37.108 0 0,1 100,298 A78.718,78.718 0 0,1 73,271 A26.239,26.239 0 0,1 82,262 A0,0 0 0,1 82,262"
    },
    {
      "id": "seg-160",
      "threadId": 4,
      "path": "M109,280 A52.479,52.479 0 0,1 127,298 A26.239,26.239 0 0,1 118,307 A26.239,26.239 0 0,1 109,298 A37.108,37.108 0 0,1 109,280 A0,0 0 0,1 109,280"
    },
    {
      "id": "seg-161",
      "threadId": 13,
      "path": "M127,298 A26.239,26.239 0 0,1 118,289 A52.479,52.479 0 0,1 136,271 A37.108,37.108 0 0,1 136,289 A26.239,26.239 0 0,1 127,298 A0,0 0 0,1 127,298"
    },
    {
      "id": "seg-162",
      "threadId": 13,
      "path": "M145,271 A52.479,52.479 0 0,1 163,253 A26.239,26.239 0 0,1 172,262 A78.718,78.718 0 0,1 145,289 A37.108,37.108 0 0,1 145,271 A0,0 0 0,1 145,271"
    },
    {
      "id": "seg-163",
      "threadId": 20,
      "path": "M163,253 A26.239,26.239 0 0,1 172,244 A52.479,52.479 0 0,1 190,262 A26.239,26.239 0 0,1 181,271 A52.479,52.479 0 0,1 163,253 A0,0 0 0,1 163,253"
    },
    {
      "id": "seg-164",
      "threadId": 9,
      "path": "M181,271 A78.718,78.718 0 0,1 208,244 A26.239,26.239 0 0,1 217,253 A78.718,78.718 0 0,1 190,280 A26.239,26.239 0 0,1 181,271 A0,0 0 0,1 181,271"
    },
    {
      "id": "seg-165",
      "threadId": 16,
      "path": "M217,253 A52.479,52.479 0 0,1 235,271 A37.108,37.108 0 0,1 235,289 A78.718,78.718 0 0,1 208,262 A26.239,26.239 0 0,1 217,253 A0,0 0 0,1 217,253"
    },
    {
      "id": "seg-166",
      "threadId": 16,
      "path": "M244,271 A52.479,52.479 0 0,1 262,289 A26.239,26.239 0 0,1 253,298 A26.239,26.239 0 0,1 244,289 A37.108,37.108 0 0,1 244,271 A0,0 0 0,1 244,271"
    },
    {
      "id": "seg-167",
      "threadId": 2,
      "path": "M262,289 A26.239,26.239 0 0,1 253,280 A52.479,52.479 0 0,1 271,262 A37.108,37.108 0 0,1 271,280 A26.239,26.239 0 0,1 262,289 A0,0 0 0,1 262,289"
    },
    {
      "id": "seg-168",
      "threadId": 0,
      "path": "M10,298 A52.479,52.479 0 0,1 28,280 A26.239,26.239 0 0,1 37,289 A78.718,78.718 0 0,1 10,316 A37.108,37.108 0 0,1 10,298 A0,0 0 0,1 10,298"
    },
    {
      "id": "seg-169",
      "threadId": 6,
      "path": "M28,280 A26.239,26.239 0 0,1 37,271 A52.479,52.479 0 0,1 55,289 A26.239,26.239 0 0,1 46,298 A52.479,52.479 0 0,1 28,280 A0,0 0 0,1 28,280"
    },
    {
      "id": "seg-170",
      "threadId": 23,
      "path": "M46,298 A78.718,78.718 0 0,1 73,271 A26.239,26.239 0 0,1 82,280 A78.718,78.718 0 0,1 55,307 A26.239,26.239 0 0,1 46,298 A0,0 0 0,1 46,298"
    },
    {
      "id": "seg-171",
      "threadId": 5,
      "path": "M82,280 A52.479,52.479 0 0,1 100,298 A37.108,37.108 0 0,1 100,316 A78.718,78.718 0 0,1 73,289 A26.239,26.239 0 0,1 82,280 A0,0 0 0,1 82,280"
    },
    {
      "id": "seg-172",
      "threadId": 5,
      "path": "M109,298 A52.479,52.479 0 0,1 127,316 A26.239,26.239 0 0,1 118,325 A26.239,26.239 0 0,1 109,316 A37.108,37.108 0 0,1 109,298 A0,0 0 0,1 109,298"
    },
    {
      "id": "seg-173",
      "threadId": 12,
      "path": "M127,316 A26.239,26.239 0 0,1 118,307 A52.479,52.479 0 0,1 136,289 A37.108,37.108 0 0,1 136,307 A26.239,26.239 0 0,1 127,316 A0,0 0 0,1 127,316"
    },
    {
      "id": "seg-174",
      "threadId": 12,
      "path": "M145,289 A52.479,52.479 0 0,1 163,271 A26.239,26.239 0 0,1 172,280 A78.718,78.718 0 0,1 145,307 A37.108,37.108 0 0,1 145,289 A0,0 0 0,1 145,289"
    },
    {
      "id": "seg-175",
      "threadId": 19,
      "path": "M163,271 A26.239,26.239 0 0,1 172,262 A52.479,52.479 0 0,1 190,280 A26.239,26.239 0 0,1 181,289 A52.479,52.479 0 0,1 163,271 A0,0 0 0,1 163,271"
    },
    {
      "id": "seg-176",
      "threadId": 10,
      "path": "M181,289 A78.718,78.718 0 0,1 208,262 A26.239,26.239 0 0,1 217,271 A78.718,78.718 0 0,1 190,298 A26.239,26.239 0 0,1 181,289 A0,0 0 0,1 181,289"
    },
    {
      "id": "seg-177",
      "threadId": 17,
      "path": "M217,271 A52.479,52.479 0 0,1 235,289 A37.108,37.108 0 0,1 235,307 A78.718,78.718 0 0,1 208,280 A26.239,26.239 0 0,1 217,271 A0,0 0 0,1 217,271"
    },
    {
      "id": "seg-178",
      "threadId": 17,
      "path": "M244,289 A52.479,52.479 0 0,1 262,307 A26.239,26.239 0 0,1 253,316 A26.239,26.239 0 0,1 244,307 A37.108,37.108 0 0,1 244,289 A0,0 0 0,1 244,289"
    },
    {
      "id": "seg-179",
      "threadId": 1,
      "path": "M262,307 A26.239,26.239 0 0,1 253,298 A52.479,52.479 0 0,1 271,280 A37.108,37.108 0 0,1 271,298 A26.239,26.239 0 0,1 262,307 A0,0 0 0,1 262,307"
    },
    {
      "id": "seg-180",
      "threadId": 20,
      "path": "M10,316 A52.479,52.479 0 0,1 28,298 A26.239,26.239 0 0,1 37,307 A78.718,78.718 0 0,1 10,334 A37.108,37.108 0 0,1 10,316 A0,0 0 0,1 10,316"
    },
    {
      "id": "seg-181",
      "threadId": 15,
      "path": "M28,298 A26.239,26.239 0 0,1 37,289 A52.479,52.479 0 0,1 55,307 A26.239,26.239 0 0,1 46,316 A52.479,52.479 0 0,1 28,298 A0,0 0 0,1 28,298"
    },
    {
      "id": "seg-182",
      "threadId": 14,
      "path": "M46,316 A78.718,78.718 0 0,1 73,289 A26.239,26.239 0 0,1 82,298 A78.718,78.718 0 0,1 55,325 A26.239,26.239 0 0,1 46,316 A0,0 0 0,1 46,316"
    },
    {
      "id": "seg-183",
      "threadId": 9,
      "path": "M82,298 A52.479,52.479 0 0,1 100,316 A37.108,37.108 0 0,1 100,334 A78.718,78.718 0 0,1 73,307 A26.239,26.239 0 0,1 82,298 A0,0 0 0,1 82,298"
    },
    {
      "id": "seg-184",
      "threadId": 9,
      "path": "M109,316 A52.479,52.479 0 0,1 127,334 A26.239,26.239 0 0,1 118,343 A26.239,26.239 0 0,1 109,334 A37.108,37.108 0 0,1 109,316 A0,0 0 0,1 109,316"
    },
    {
      "id": "seg-185",
      "threadId": 8,
      "path": "M127,334 A26.239,26.239 0 0,1 118,325 A52.479,52.479 0 0,1 136,307 A37.108,37.108 0 0,1 136,325 A26.239,26.239 0 0,1 127,334 A0,0 0 0,1 127,334"
    },
    {
      "id": "seg-186",
      "threadId": 8,
      "path": "M145,307 A52.479,52.479 0 0,1 163,289 A26.239,26.239 0 0,1 172,298 A78.718,78.718 0 0,1 145,325 A37.108,37.108 0 0,1 145,307 A0,0 0 0,1 145,307"
    },
    {
      "id": "seg-187",
      "threadId": 18,
      "path": "M163,289 A26.239,26.239 0 0,1 172,280 A52.479,52.479 0 0,1 190,298 A26.239,26.239 0 0,1 181,307 A52.479,52.479 0 0,1 163,289 A0,0 0 0,1 163,289"
    },
    {
      "id": "seg-188",
      "threadId": 11,
      "path": "M181,307 A78.718,78.718 0 0,1 208,280 A26.239,26.239 0 0,1 217,289 A78.718,78.718 0 0,1 190,316 A26.239,26.239 0 0,1 181,307 A0,0 0 0,1 181,307"
    },
    {
      "id": "seg-189",
      "threadId": 21,
      "path": "M217,289 A52.479,52.479 0 0,1 235,307 A37.108,37.108 0 0,1 235,325 A78.718,78.718 0 0,1 208,298 A26.239,26.239 0 0,1 217,289 A0,0 0 0,1 217,289"
    },
    {
      "id": "seg-190",
      "threadId": 21,
      "path": "M244,307 A52.479,52.479 0 0,1 262,325 A26.239,26.239 0 0,1 253,334 A26.239,26.239 0 0,1 244,325 A37.108,37.108 0 0,1 244,307 A0,0 0 0,1 244,307"
    },
    {
      "id": "seg-191",
      "threadId": 0,
      "path": "M262,325 A26.239,26.239 0 0,1 253,316 A52.479,52.479 0 0,1 271,298 A37.108,37.108 0 0,1 271,316 A26.239,26.239 0 0,1 262,325 A0,0 0 0,1 262,325"
    }
  ],
  "assets": {
    "surfaceSvg": "../svgs/mitake-24.svg"
  }
}
